wpdwf/__init__.py
wpdwf/__main__.py
wpdwf/analoginstruments.py
wpdwf/deviceconfiguration.py
wpdwf/digitalinstruments.py
wpdwf/dwfexeptions.py
wpdwf/dwfresource.py
wpdwf/enumfuncconstants.py
wpdwf/wfcommoninstruments.py
wpdwf/wfoptionsconstants.py
wpdwf-0.0.1.dist-info/licenses/LICENSE
wpdwf-0.0.1.dist-info/METADATA
wpdwf-0.0.1.dist-info/WHEEL
wpdwf-0.0.1.dist-info/top_level.txt
wpdwf-0.0.1.dist-info/RECORD
