Metadata-Version: 2.4
Name: wpdwf
Version: 0.0.1
Summary: Wrapper over Waveforms SDK - application runtime
Author-email: Bogdan Stănese <bogdan.stanese@digilent.ro>
License-Expression: MIT
Classifier: Topic :: Software Development
Classifier: Programming Language :: Python :: 3
Classifier: Operating System :: OS Independent
Requires-Python: >=3.12
License-File: LICENSE
Dynamic: license-file
